pysnoo2/__init__.py
pysnoo2/auth_session.py
pysnoo2/const.py
pysnoo2/models.py
pysnoo2/oauth2_session.py
pysnoo2/pubnub.py
pysnoo2/snoo.py
pysnoo2-0.3.4.data/scripts/snoo
pysnoo2-0.3.4.dist-info/LICENSE
pysnoo2-0.3.4.dist-info/METADATA
pysnoo2-0.3.4.dist-info/WHEEL
pysnoo2-0.3.4.dist-info/top_level.txt
pysnoo2-0.3.4.dist-info/RECORD
